<annotation verified="yes">
	<folder>images</folder>
	<filename>00_image.002991.jpg</filename>
	<path>/home/quest/dark/dl/temp/passright/images/00_image.002991.jpg</path>
	<source>
		<database>Unknown</database>
	</source>
	<size>
		<width>1628</width>
		<height>1236</height>
		<depth>3</depth>
	</size>
	<segmented>0</segmented>
	<object>
		<name>passright</name>
		<pose>Unspecified</pose>
		<truncated>0</truncated>
		<difficult>0</difficult>
		<bndbox>
			<xmin>423</xmin>
			<ymin>70</ymin>
			<xmax>514</xmax>
			<ymax>161</ymax>
		</bndbox>
	</object>
	<object>
		<name>passright</name>
		<pose>Unspecified</pose>
		<truncated>0</truncated>
		<difficult>0</difficult>
		<bndbox>
			<xmin>1408</xmin>
			<ymin>230</ymin>
			<xmax>1463</xmax>
			<ymax>287</ymax>
		</bndbox>
	</object>
</annotation>
